reflex_katex/__init__.py
reflex_katex/katex.py
reflex_katex-0.0.3.dist-info/METADATA
reflex_katex-0.0.3.dist-info/WHEEL
reflex_katex-0.0.3.dist-info/RECORD
